[   
    {
        "title":"首页",
        "path":"/home/home",
        "child":[]
    },
    {
        "title":"监控中心",
        "path":"/visual",
        "child":[]
    },
    {
        "title":"监控视频",
        "path":"/watch",
        "child":[]
    },
    {
        "title":"指挥中心",
        "path":"/home/command",
        "child":[
            {
                "title":"现场监控",
                "path":"/home/command/site", 
                "child":[
                ]
            },
            {
                "title":"实时指控",
                "path":"/home/command/watch", 
                "child":[
                ]
            }
            ,
            {
                "title":"工作计划",
                "path":"/home/command/plan", 
                "child":[
                ]
            }
            ,
            {
                "title":"历史轨迹",
                "path":"/home/command/history", 
                "child":[
                ]
            }
            ,
            {
                "title":"消息推送",
                "path":"/home/command/message", 
                "child":[
                ]
            }
            ,
            {
                "title":"集群对讲",
                "path":"/home/command/talk", 
                "child":[
                ]
            },
            {
                "title":"SOS求救",
                "path":"/home/command/SOS", 
                "child":[
                ]
            },
            {
                "title":"围栏告警",
                "path":"/home/command/alarm", 
                "child":[
                ]
            },
            {
                "title":"围栏配置",
                "path":"/home/command/config", 
                "child":[
                ]
            },
            {
                "title":"监控视频配置",
                "path":"/home/command/videoConfig", 
                "child":[
                ]
            },
            {
                "title":"远程控制",
                "path":"/home/command/remote", 
                "child":[
                    {
                        "title":"重启终端",
                        "path":"/home/command/remote/restart"
                    }
                ]
            }
        ]
    },
    {
        "title":"视频管理",
        "path":"/home/video",
        "child":[
            {
                "title":"视频回放",
                "path":"/home/video/replay", 
                "child":[
                ]
            },
            {
                "title":"视频挖掘",
                "path":"/home/video/read", 
                "child":[
                    {
                        "title":"车牌识别",
                        "path":"/home/video/read/car", 
                        "child":[
                        ]
                    },
                    {
                        "title":"人脸识别",
                        "path":"/home/video/read/face", 
                        "child":[
                        ]
                    },
                    {
                        "title":"人脸追踪",
                        "path":"/home/video/read/track", 
                        "child":[
                        ]
                    }
                ]
            }
        ]
    },
    {
        "title":"考勤管理",
        "path":"/home/work",
        "child":[
            {
                "title":"考勤统计",
                "path":"/home/work/check", 
                "child":[
                ]
            },
            {
                "title":"排班管理",
                "path":"/home/work/order", 
                "child":[
                ]
            },
            {
                "title":"考勤设置",
                "path":"/home/work/config", 
                "child":[
                ]
            },
            {
                "title":"GIS签到",
                "path":"/home/work/gis", 
                "child":[
                ]
            },
            {
                "title":"异常提醒",
                "path":"/home/work/abnormal", 
                "child":[
                ]
            }
        ]
    },
    {
        "title":"统计分析",
        "path":"/home/chart",
        "child":[
            {
                "title":"基本数据分析",
                "path":"/home/chart/base", 
                "child":[
                ]
            },
            {
                "title":"趋势图",
                "path":"/home/chart/trend", 
                "child":[
                ]
            },
            {
                "title":"趋势对比图",
                "path":"/home/chart/compare", 
                "child":[
                ]
            }
        ]
    },
    {
        "title":"设备管理",
        "path":"/home/device",
        "child":[
            {
                "title":"设备管理",
                "path":"/home/device/manager", 
                "child":[
                ]
            },
            {
                "title":"设备维修管理",
                "path":"/home/device/repair", 
                "child":[
                ]
            },
            {
                "title":"设备运行情况",
                "path":"/home/device/state", 
                "child":[
                ]
            },
            {
                "title":"设备类型",
                "path":"/home/device/type", 
                "child":[
                ]
            },
            {
                "title":"设备升级包管理",
                "path":"/home/device/update", 
                "child":[
                ]
            }
        ]
    },
    {
        "title":"权限管理",
        "path":"/home/role",
        "child":[
            {
                "title":"用户管理",
                "path":"/home/role/user", 
                "child":[
                ]
            },
            {
                "title":"角色管理",
                "path":"/home/role/role", 
                "child":[
                ]
            },
            {
                "title":"单位管理",
                "path":"/home/role/unit", 
                "child":[
                ]
            }
        ]
    },
    {
        "title":"系统管理",
        "path":"/home/system",
        "child":[
            {
                "title":"群组设置",
                "path":"/home/system/group", 
                "child":[
                ]
            },
            {
                "title":"消息记录",
                "path":"/home/system/message", 
                "child":[
                ]
            },
            {
                "title":"工作站管理",
                "path":"/home/system/site", 
                "child":[
                ]
            },
            {
                "title":"基本资料设置",
                "path":"/home/system/base", 
                "child":[
                ]
            },
            {
                "title":"系统配置项",
                "path":"/home/system/config", 
                "child":[
                ]
            },
            {
                "title":"GIS系统配置",
                "path":"/home/system/gis", 
                "child":[
                ]
            }
        ]
    },
    {
        "title":"日志管理",
        "path":"/home/log",
        "child":[
            {
                "title":"系统日志",
                "path":"/home/log/systemLog", 
                "child":[
                ]
            },
            {
                "title":"记录仪日志",
                "path":"/home/log/deviceLog", 
                "child":[
                ]
            },
            {
                "title":"工作站日志",
                "path":"/home/log/siteLog", 
                "child":[
                ]
            }
        ]
    }
]